LICENSE
README.md
setup.py
datetimetounix/__init__.py
datetimetounix/convert.py
datetimetounix.egg-info/PKG-INFO
datetimetounix.egg-info/SOURCES.txt
datetimetounix.egg-info/dependency_links.txt
datetimetounix.egg-info/top_level.txt